README.txt
setup.py
kw_ppjp.chat.egg-info/PKG-INFO
kw_ppjp.chat.egg-info/SOURCES.txt
kw_ppjp.chat.egg-info/dependency_links.txt
kw_ppjp.chat.egg-info/top_level.txt
ppjp/chat/__init__.py
ppjp/chat/client.py
ppjp/chat/server.py