Metadata-Version: 1.1
Name: kw-ppjp.chat
Version: 0.1
Summary: a simple gui chat application
Home-page: http://pypi.python.org/ppjp.chat
Author: Perfect Python
Author-email: ppjp@perfoectpython.jp
License: UNKNOWN
Platform: UNKNOWN
Classifier: Development Status :: 3 - Alpha
Classifier: Programming Language :: Python :: 3
Classifier: Programming Language :: Python :: 3.3
Classifier: Topic :: Communications :: Chat
